ladybug_geometry/__init__.py
ladybug_geometry/_mesh.py
ladybug_geometry/_polyline.py
ladybug_geometry/boolean.py
ladybug_geometry/bounding.py
ladybug_geometry/dictutil.py
ladybug_geometry/intersection2d.py
ladybug_geometry/intersection3d.py
ladybug_geometry/network.py
ladybug_geometry/projection.py
ladybug_geometry/triangulation.py
ladybug_geometry/geometry2d/_1d.py
ladybug_geometry/geometry2d/_2d.py
ladybug_geometry/geometry2d/__init__.py
ladybug_geometry/geometry2d/arc.py
ladybug_geometry/geometry2d/line.py
ladybug_geometry/geometry2d/mesh.py
ladybug_geometry/geometry2d/pointvector.py
ladybug_geometry/geometry2d/polygon.py
ladybug_geometry/geometry2d/polyline.py
ladybug_geometry/geometry2d/ray.py
ladybug_geometry/geometry3d/_1d.py
ladybug_geometry/geometry3d/_2d.py
ladybug_geometry/geometry3d/__init__.py
ladybug_geometry/geometry3d/arc.py
ladybug_geometry/geometry3d/cone.py
ladybug_geometry/geometry3d/cylinder.py
ladybug_geometry/geometry3d/face.py
ladybug_geometry/geometry3d/line.py
ladybug_geometry/geometry3d/mesh.py
ladybug_geometry/geometry3d/plane.py
ladybug_geometry/geometry3d/pointvector.py
ladybug_geometry/geometry3d/polyface.py
ladybug_geometry/geometry3d/polyline.py
ladybug_geometry/geometry3d/ray.py
ladybug_geometry/geometry3d/sphere.py
ladybug_geometry/interop/__init__.py
ladybug_geometry/interop/obj.py
ladybug_geometry/interop/stl.py
ladybug_geometry-1.34.16.dist-info/licenses/LICENSE
ladybug_geometry-1.34.16.dist-info/METADATA
ladybug_geometry-1.34.16.dist-info/WHEEL
ladybug_geometry-1.34.16.dist-info/top_level.txt
ladybug_geometry-1.34.16.dist-info/RECORD
